plantanno/__init__.py
plantanno/cli.py
plantanno/config.py
plantanno/pipelines.py
plantanno/src.py
plantanno/versions.py
PlantAnno-0.2.6.dist-info/LICENSE
PlantAnno-0.2.6.dist-info/METADATA
PlantAnno-0.2.6.dist-info/WHEEL
PlantAnno-0.2.6.dist-info/entry_points.txt
PlantAnno-0.2.6.dist-info/top_level.txt
PlantAnno-0.2.6.dist-info/RECORD
