Metadata-Version: 2.1
Name: PlantAnno
Version: 0.2.6
Summary: An automated process for plant genome annotation
Home-page: https://github.com/SouthernCD/PlantAnno
Author: Yuxing Xu
Author-email: xuyuxing@mail.kib.ac.cn
License: UNKNOWN
Platform: UNKNOWN
Requires-Python: >=3.5
License-File: LICENSE
Requires-Dist: toolbiox (>=0.0.15)
Requires-Dist: interlap (>=0.2.6)
Requires-Dist: bioseqtools (>=0.2.0)
